hugie/__init__.py
hugie/__main__.py
hugie/config.py
hugie/endpoint.py
hugie/exceptions.py
hugie/models.py
hugie/settings.py
hugie/utils.py
hugie-0.4.0.dist-info/LICENSE
hugie-0.4.0.dist-info/METADATA
hugie-0.4.0.dist-info/WHEEL
hugie-0.4.0.dist-info/entry_points.txt
hugie-0.4.0.dist-info/RECORD
