Metadata-Version: 2.1
Name: hugie
Version: 0.4.0
Summary: CLI for managing Hugging Face Inference Endpoints
License: MIT
Author: Matthew Upson
Author-email: matt@mantisnlp.com
Requires-Python: >=3.9,<4.0
Classifier: License :: OSI Approved :: MIT License
Classifier: Programming Language :: Python :: 3
Classifier: Programming Language :: Python :: 3.9
Classifier: Programming Language :: Python :: 3.10
Classifier: Programming Language :: Python :: 3.11
Requires-Dist: pydantic (>=2.0.3,<3.0.0)
Requires-Dist: pydantic-settings (>=2.0.2,<3.0.0)
Requires-Dist: pytest-mock (>=3.11.1,<4.0.0)
Requires-Dist: requests (>=2.31.0,<3.0.0)
Requires-Dist: srsly (>=2.4.7,<3.0.0)
Requires-Dist: typer (>=0.9.0,<0.10.0)
Requires-Dist: wasabi (>=1.1.2,<2.0.0)
